compartor/__init__.py
compartor/automated.py
compartor/closure.py
compartor/codegen.py
compartor/compartments.py
compartor/display.py
compartor/syntactic_sugar.py
compartor-1.1.1.dist-info/LICENSE.txt
compartor-1.1.1.dist-info/METADATA
compartor-1.1.1.dist-info/WHEEL
compartor-1.1.1.dist-info/top_level.txt
compartor-1.1.1.dist-info/RECORD
