Metadata-Version: 2.1
Name: compartor
Version: 1.1.1
Summary: Automatic moment equation generation for stochastic compartment populations
Home-page: http://github.com/zechnerlab/Compartor
Author: Tobias Pietzsch
Author-email: tobias.pietzsch@gmail.com
License: Simplified BSD License
Platform: UNKNOWN
Requires-Python: >=3
Requires-Dist: sympy (>=1.6)
Requires-Dist: ipython (>=7.13)
